LICENSE
MANIFEST.in
README
VERSION
setup.py
ccv/ccv.cpp
ccv/ccv.hpp
src/pyccv/__init__.py
src/pyccv.egg-info/PKG-INFO
src/pyccv.egg-info/SOURCES.txt
src/pyccv.egg-info/dependency_links.txt
src/pyccv.egg-info/requires.txt
src/pyccv.egg-info/top_level.txt
test/test.bmp
test/test_ccv.py