Metadata-Version: 1.0
Name: pyccv
Version: 0.05
Summary: Calculate color coherence vector for similar image search
Home-page: http://www.bitbucket.org/ynil/pyccv
Author: Shunsuke Aihara
Author-email: s.aihara@gmail.com
License: MIT License
Keywords: image-processing computer-vision
Platform: UNKNOWN
